AUTHORS.rst
CONTRIBUTING.rst
HISTORY.rst
LICENSE
MANIFEST.in
README.rst
setup.cfg
setup.py
django_json_schema/__init__.py
django_json_schema/cli.py
django_json_schema/django_json_schema.py
django_json_schema.egg-info/PKG-INFO
django_json_schema.egg-info/SOURCES.txt
django_json_schema.egg-info/dependency_links.txt
django_json_schema.egg-info/entry_points.txt
django_json_schema.egg-info/not-zip-safe
django_json_schema.egg-info/requires.txt
django_json_schema.egg-info/top_level.txt
docs/Makefile
docs/authors.rst
docs/conf.py
docs/contributing.rst
docs/history.rst
docs/index.rst
docs/installation.rst
docs/make.bat
docs/readme.rst
docs/usage.rst
tests/__init__.py
tests/test_django_json_schema.py