Metadata-Version: 1.1
Name: django-json-schema
Version: 0.1.0
Summary: Creates json schema from django models
Home-page: https://github.com/tom-zeit/django_json_schema
Author: Tom Raz
Author-email: tom@zeitgold.com
License: MIT license
Keywords: django_json_schema
Platform: UNKNOWN
Classifier: Development Status :: 2 - Pre-Alpha
Classifier: Intended Audience :: Developers
Classifier: License :: OSI Approved :: MIT License
Classifier: Natural Language :: English
Classifier: Programming Language :: Python :: 2
Classifier: Programming Language :: Python :: 2.6
Classifier: Programming Language :: Python :: 2.7
Classifier: Programming Language :: Python :: 3
Classifier: Programming Language :: Python :: 3.3
Classifier: Programming Language :: Python :: 3.4
Classifier: Programming Language :: Python :: 3.5
